{
	"map_name": "Lagoon-class Cruise Ship",
	"prefix": "ISV",
	"namelists": ["CRUISE"],
	"map_short_name": "Lagoon-class",
	"map_path": "_maps/shuttles/shiptest/tour_cruise_ship.dmm",
	"map_id": "tour_cruise_ship",
	"job_slots": {
		"Капитан": 1,
		"Директор круиза": {
			"outfit": "/datum/outfit/job/head_of_personnel",
			"slots": 1
		},
		"Офицер": 2,
		"Врач": 1,
		"Корабельный Инженер": {
			"outfit": "/datum/outfit/job/atmos",
			"slots": 1
		},
		"Бармен": 1,
		"Повар": 1,
		"Ботаник": 1,
		"Куратор": 1,
		"Капеллан": 1,
		"Уборщик": 1,
		"Клоун": 1,
		"Мим": 1,
		"Пассажир": {
			"outfit": "/datum/outfit/job/assistant/corporate",
			"slots": 10
		}
	},
	"cost": 600
}
